{"file":"SideNav-C_vDSpzB.js","mappings":";;;;;;;;;;;;;;;;AA+BA,UAAM,QAAQ,SAAU;AACxB,UAAM,QAAQ,IAAI,EAAE;;;;;;;;;;;;;;;;;;;;;;;;;;;;;;;;;;;;;;;;;;","names":[],"sources":["../../../../components/SideNav/SideNav.vue"],"sourcesContent":["<template>\r\n  <aside class=\"sidebar h-100 d-flex flex-column\">\r\n    <div class=\"widget category mb-4\">\r\n      <h5 class=\"widget-title\">\r\n        <a href=\"#\" @click.prevent>{{ title }}</a>\r\n      </h5>\r\n      <div class=\"category-list list-group\" v-if=\"links.length\">\r\n        <NuxtLink\r\n          v-for=\"(link, index) in links\"\r\n          :key=\"index\"\r\n          :to=\"`${baseRoute}/${link.path}`\"\r\n          class=\"list-group-item list-group-item-action d-flex justify-content-between align-items-center\"\r\n          :class=\"{ active: route.params.section === link.path }\"\r\n        >\r\n          <span><i class=\"fa-solid fa-arrow-right me-2\"></i>{{ link.label }}</span>\r\n        </NuxtLink>\r\n      </div>\r\n    </div>\r\n  </aside>\r\n</template>\r\n\r\n<script setup>\r\nimport { ref, onMounted } from 'vue'\r\nimport { useRoute } from 'vue-router'\r\n\r\nconst props = defineProps({\r\n  title: { type: String, default: 'Navigation' },\r\n  sectionKey: { type: String, required: true },  // e.g., \"aboutUs\"\r\n  baseRoute: { type: String, required: true }    // e.g., \"/aboutUs\"\r\n})\r\n\r\nconst route = useRoute()\r\nconst links = ref([])\r\n\r\nconst fetchLinks = async () => {\r\n  try {\r\n    const raw = await $fetch('/data/sidebarLinks.txt')\r\n    const sections = raw.split(';')\r\n\r\n    for (const section of sections) {\r\n      const [key, value] = section.split('=')\r\n      if (key?.trim() === props.sectionKey) {\r\n        links.value = value\r\n          .split(',')\r\n          .map(item => {\r\n            const [label, path] = item.split('|')\r\n            return path?.trim() ? { label: label.trim(), path: path.trim() } : null\r\n          })\r\n          .filter(Boolean)\r\n        break\r\n      }\r\n    }\r\n  } catch (err) {\r\n    console.error('Sidebar fetch error:', err)\r\n  }\r\n}\r\n\r\nonMounted(fetchLinks)\r\n</script>\r\n\r\n<style scoped>  \r\n.list-group-item.active {\r\n  text-decoration: underline;\r\n  color: var(--theme-color, #ffc107); /* matches txt-warning */\r\n}\r\n.blog-single-area {\r\n  background: #fff;\r\n}\r\n\r\n.widget {\r\n  background: var(--theme-bg-light);\r\n  padding: 30px;\r\n  margin-bottom: 30px;\r\n}\r\n\r\n.widget .widget-title {\r\n  padding-bottom: 10px;\r\n  margin-bottom: 30px;\r\n  position: relative;\r\n  font-size: 22px;\r\n  color: var(--color-dark);\r\n}\r\n\r\n.widget .widget-title::before,\r\n.widget .widget-title::after {\r\n  content: '';\r\n  position: absolute;\r\n  bottom: 0;\r\n  border-bottom: 3px solid var(--theme-color);\r\n}\r\n\r\n.widget .widget-title::before {\r\n  width: 15px;\r\n  left: 0;\r\n}\r\n\r\n.widget .widget-title::after {\r\n  width: 30px;\r\n  left: 22px;\r\n}\r\n\r\n.widget .category-list a {\r\n  padding: 10px 0;\r\n  background: #f2f3f5;\r\n  border: none;\r\n  border-bottom: 1px solid #ced4da;\r\n  font-weight: 500;\r\n  transition: var(--transition);\r\n}\r\n\r\n.widget .category-list a:last-child {\r\n  border-bottom: none;\r\n}\r\n\r\n.widget .category-list a:hover {\r\n  padding-left: 10px;\r\n  color: var(--theme-color);\r\n}\r\n\r\n.widget .category-list a i {\r\n  margin-right: 5px;\r\n  color: var(--theme-color);\r\n}\r\n\r\n/* About section */\r\n.blog-single-content section#about {\r\n  padding: 5rem 0;\r\n}\r\naside.sidebar {\r\n    background: var(--theme-bg-light);\r\n}\r\n</style>\r\n"],"version":3}